{
  "resolvedId": "C:/Users/MAG/IdeaProjects/Datenanalysetool/src/main/vue-project/node_modules/vuetify/lib/components/VApp/VApp.css",
  "transforms": [
    {
      "name": "vite:load-fallback",
      "result": ".v-application {\n  display: flex;\n  background: rgb(var(--v-theme-background));\n  color: rgba(var(--v-theme-on-background), var(--v-high-emphasis-opacity));\n}\n\n.v-application__wrap {\n  backface-visibility: hidden;\n  display: flex;\n  flex-direction: column;\n  flex: 1 1 auto;\n  max-width: 100%;\n  min-height: 100vh;\n  min-height: 100dvh;\n  position: relative;\n}",
      "start": 1723904397606,
      "end": 1723904397625,
      "sourcemaps": null
    },
    {
      "name": "vite:css",
      "result": ".v-application {\n  display: flex;\n  background: rgb(var(--v-theme-background));\n  color: rgba(var(--v-theme-on-background), var(--v-high-emphasis-opacity));\n}\n\n.v-application__wrap {\n  backface-visibility: hidden;\n  display: flex;\n  flex-direction: column;\n  flex: 1 1 auto;\n  max-width: 100%;\n  min-height: 100vh;\n  min-height: 100dvh;\n  position: relative;\n}",
      "start": 1723904397625,
      "end": 1723904397625,
      "order": "normal",
      "sourcemaps": null
    },
    {
      "name": "vite:esbuild",
      "start": 1723904397625,
      "end": 1723904397625,
      "order": "normal"
    },
    {
      "name": "vite:json",
      "start": 1723904397625,
      "end": 1723904397625,
      "order": "normal"
    },
    {
      "name": "vite:worker",
      "start": 1723904397625,
      "end": 1723904397625,
      "order": "normal"
    },
    {
      "name": "vite:vue",
      "start": 1723904397625,
      "end": 1723904397625,
      "order": "normal"
    },
    {
      "name": "vite:define",
      "start": 1723904397625,
      "end": 1723904397625,
      "order": "normal"
    },
    {
      "name": "vite:css-post",
      "result": "",
      "start": 1723904397625,
      "end": 1723904397625,
      "order": "normal",
      "sourcemaps": {
        "mappings": ""
      }
    },
    {
      "name": "vite:build-html",
      "start": 1723904397625,
      "end": 1723904397625,
      "order": "normal"
    },
    {
      "name": "vite:worker-import-meta-url",
      "start": 1723904397625,
      "end": 1723904397625,
      "order": "normal"
    },
    {
      "name": "vite:asset-import-meta-url",
      "start": 1723904397625,
      "end": 1723904397625,
      "order": "normal"
    },
    {
      "name": "commonjs",
      "start": 1723904397625,
      "end": 1723904397625,
      "order": "normal"
    },
    {
      "name": "vite:dynamic-import-vars",
      "start": 1723904397625,
      "end": 1723904397625,
      "order": "normal"
    },
    {
      "name": "vite:import-glob",
      "start": 1723904397625,
      "end": 1723904397626,
      "order": "normal"
    },
    {
      "name": "vite:build-import-analysis",
      "start": 1723904397626,
      "end": 1723904397626,
      "order": "normal"
    },
    {
      "name": "vite:reporter",
      "start": 1723904397626,
      "end": 1723904397626,
      "order": "normal"
    }
  ]
}
