{
  "resolvedId": "C:/Users/MAG/IdeaProjects/Datenanalysetool/src/main/vue-project/node_modules/vuetify/lib/components/VKbd/index.mjs",
  "transforms": [
    {
      "name": "vite:load-fallback",
      "result": "// Styles\nimport \"./VKbd.css\";\n\n// Utilities\nimport { createSimpleFunctional } from \"../../util/index.mjs\";\nexport const VKbd = createSimpleFunctional('v-kbd');\n//# sourceMappingURL=index.mjs.map",
      "start": 1724718167969,
      "end": 1724718168065,
      "sourcemaps": null
    },
    {
      "name": "vite:css",
      "start": 1724718168066,
      "end": 1724718168066,
      "order": "normal"
    },
    {
      "name": "vite:esbuild",
      "start": 1724718168066,
      "end": 1724718168066,
      "order": "normal"
    },
    {
      "name": "vite:json",
      "start": 1724718168066,
      "end": 1724718168066,
      "order": "normal"
    },
    {
      "name": "vite:worker",
      "start": 1724718168066,
      "end": 1724718168066,
      "order": "normal"
    },
    {
      "name": "vite:vue",
      "start": 1724718168066,
      "end": 1724718168066,
      "order": "normal"
    },
    {
      "name": "vite:define",
      "start": 1724718168066,
      "end": 1724718168066,
      "order": "normal"
    },
    {
      "name": "vite:css-post",
      "start": 1724718168066,
      "end": 1724718168066,
      "order": "normal"
    },
    {
      "name": "vite:build-html",
      "start": 1724718168066,
      "end": 1724718168066,
      "order": "normal"
    },
    {
      "name": "vite:worker-import-meta-url",
      "start": 1724718168066,
      "end": 1724718168066,
      "order": "normal"
    },
    {
      "name": "vite:asset-import-meta-url",
      "start": 1724718168066,
      "end": 1724718168066,
      "order": "normal"
    },
    {
      "name": "commonjs",
      "start": 1724718168066,
      "end": 1724718168066,
      "order": "normal"
    },
    {
      "name": "vite:dynamic-import-vars",
      "start": 1724718168066,
      "end": 1724718168066,
      "order": "normal"
    },
    {
      "name": "vite:import-glob",
      "start": 1724718168066,
      "end": 1724718168066,
      "order": "normal"
    },
    {
      "name": "vite:build-import-analysis",
      "start": 1724718168066,
      "end": 1724718168066,
      "order": "normal"
    },
    {
      "name": "vite:reporter",
      "start": 1724718168066,
      "end": 1724718168066,
      "order": "normal"
    }
  ]
}
