{
  "resolvedId": "C:/Users/MAG/IdeaProjects/Datenanalysetool/src/main/vue-project/node_modules/vuetify/lib/components/VGrid/VSpacer.mjs",
  "transforms": [
    {
      "name": "vite:load-fallback",
      "result": "// Styles\nimport \"./VGrid.css\";\n\n// Utilities\nimport { createSimpleFunctional } from \"../../util/index.mjs\";\nexport const VSpacer = createSimpleFunctional('v-spacer', 'div', 'VSpacer');\n//# sourceMappingURL=VSpacer.mjs.map",
      "start": 1722584660002,
      "end": 1722584660007,
      "sourcemaps": null
    }
  ]
}
