{
  "resolvedId": "C:/Users/MAG/IdeaProjects/Datenanalysetool/src/main/vue-project/src/App.vue?vue&type=style&index=0&scoped=a872ff5e&lang.css",
  "transforms": [
    {
      "name": "vite:vue",
      "result": "\nheader {\n  line-height: 1.5;\n}\n\n.logo {\n  display: block;\n  margin: 0 auto 2rem;\n}\n\n@media (min-width: 1024px) {\n  header {\n    display: flex;\n    place-items: center;\n    padding-right: calc(var(--section-gap) / 2);\n  }\n\n  .logo {\n    margin: 0 2rem 0 0;\n  }\n\n  header .wrapper {\n    display: flex;\n    place-items: flex-start;\n    flex-wrap: wrap;\n  }\n}\n",
      "start": 1723495916825,
      "end": 1723495916826,
      "sourcemaps": {
        "version": 3,
        "sources": [
          "C:/Users/MAG/IdeaProjects/Datenanalysetool/src/main/vue-project/src/App.vue"
        ],
        "names": [],
        "mappings": ";AAwCA,CAAC,CAAC,CAAC,CAAC,CAAC,EAAE;EACL,CAAC,CAAC,CAAC,CAAC,CAAC,CAAC,CAAC,CAAC,CAAC,CAAC,CAAC,EAAE,CAAC,CAAC,CAAC;AAClB;;AAEA,CAAC,CAAC,CAAC,CAAC,EAAE;EACJ,CAAC,CAAC,CAAC,CAAC,CAAC,CAAC,CAAC,EAAE,CAAC,CAAC,CAAC,CAAC,CAAC;EACd,CAAC,CAAC,CAAC,CAAC,CAAC,CAAC,EAAE,EAAE,CAAC,CAAC,CAAC,EAAE,CAAC,CAAC,CAAC,CAAC;AACrB;;AAEA,CAAC,CAAC,CAAC,CAAC,CAAC,EAAE,CAAC,CAAC,CAAC,CAAC,CAAC,CAAC,CAAC,CAAC,CAAC,CAAC,EAAE,CAAC,CAAC,CAAC,CAAC,CAAC,CAAC,EAAE;EACzB,CAAC,CAAC,CAAC,CAAC,CAAC,EAAE;IACL,CAAC,CAAC,CAAC,CAAC,CAAC,CAAC,CAAC,EAAE,CAAC,CAAC,CAAC,CAAC;IACb,CAAC,CAAC,CAAC,CAAC,CAAC,CAAC,CAAC,CAAC,CAAC,CAAC,CAAC,EAAE,CAAC,CAAC,CAAC,CAAC,CAAC,CAAC;IACnB,CAAC,CAAC,CAAC,CAAC,CAAC,CAAC,CAAC,CAAC,CAAC,CAAC,CAAC,CAAC,CAAC,EAAE,CAAC,CAAC,CAAC,CAAC,CAAC,CAAC,CAAC,CAAC,CAAC,CAAC,CAAC,CAAC,CAAC,CAAC,CAAC,CAAC,CAAC,CAAC,CAAC,CAAC,CAAC,CAAC,EAAE,EAAE,CAAC,CAAC;EAC7C;;EAEA,CAAC,CAAC,CAAC,CAAC,EAAE;IACJ,CAAC,CAAC,CAAC,CAAC,CAAC,CAAC,EAAE,EAAE,CAAC,CAAC,CAAC,EAAE,EAAE,CAAC;EACpB;;EAEA,CAAC,CAAC,CAAC,CAAC,CAAC,EAAE,CAAC,CAAC,CAAC,CAAC,CAAC,CAAC,CAAC,EAAE;IACd,CAAC,CAAC,CAAC,CAAC,CAAC,CAAC,CAAC,EAAE,CAAC,CAAC,CAAC,CAAC;IACb,CAAC,CAAC,CAAC,CAAC,CAAC,CAAC,CAAC,CAAC,CAAC,CAAC,CAAC,EAAE,CAAC,CAAC,CAAC,CAAC,CAAC,CAAC,CAAC,CAAC,CAAC,CAAC;IACvB,CAAC,CAAC,CAAC,CAAC,CAAC,CAAC,CAAC,CAAC,CAAC,EAAE,CAAC,CAAC,CAAC,CAAC;EACjB;AACF",
        "file": "C:/Users/MAG/IdeaProjects/Datenanalysetool/src/main/vue-project/src/App.vue",
        "sourceRoot": "",
        "sourcesContent": [
          "<script setup lang=\"ts\">\nimport { ref } from 'vue'\nimport { useTheme } from 'vuetify'\n\n\n// Theme-Setup\nconst theme = useTheme()\nconst appTitle = ref('HeimAG Datenanalysetool')\n\n\n// Funktion zum Umschalten des Themas\nfunction toggleTheme() {\n  theme.global.name.value = theme.global.current.value.dark ? 'light' : 'dark'\n}\n\nfunction logout() {\n  location.href = '/logout'\n}\n\n\n</script>\n\n<template>\n  <v-app>\n    <v-responsive class=\"border rounded\">\n      <v-app-bar class=\"px-3\">\n        <v-app-bar-title>{{ appTitle }}</v-app-bar-title>\n        <v-btn @click=\"toggleTheme\" icon=\"mdi-theme-light-dark\" />\n        <v-btn @click=\"logout\" icon=\"mdi-logout\" />\n      </v-app-bar>\n      <v-main>\n        <v-container>\n          <RouterView />\n        </v-container>\n      </v-main>\n    </v-responsive>\n  </v-app>\n</template>\n\n<style scoped>\nheader {\n  line-height: 1.5;\n}\n\n.logo {\n  display: block;\n  margin: 0 auto 2rem;\n}\n\n@media (min-width: 1024px) {\n  header {\n    display: flex;\n    place-items: center;\n    padding-right: calc(var(--section-gap) / 2);\n  }\n\n  .logo {\n    margin: 0 2rem 0 0;\n  }\n\n  header .wrapper {\n    display: flex;\n    place-items: flex-start;\n    flex-wrap: wrap;\n  }\n}\n</style>\n\n"
        ]
      }
    },
    {
      "name": "vite:css",
      "result": "\nheader {\n  line-height: 1.5;\n}\n\n.logo {\n  display: block;\n  margin: 0 auto 2rem;\n}\n\n@media (min-width: 1024px) {\n  header {\n    display: flex;\n    place-items: center;\n    padding-right: calc(var(--section-gap) / 2);\n  }\n\n  .logo {\n    margin: 0 2rem 0 0;\n  }\n\n  header .wrapper {\n    display: flex;\n    place-items: flex-start;\n    flex-wrap: wrap;\n  }\n}\n",
      "start": 1723495916827,
      "end": 1723495921156,
      "order": "normal",
      "sourcemaps": null
    },
    {
      "name": "vite:esbuild",
      "start": 1723495921158,
      "end": 1723495921159,
      "order": "normal"
    },
    {
      "name": "vite:json",
      "start": 1723495921159,
      "end": 1723495921159,
      "order": "normal"
    },
    {
      "name": "vite:worker",
      "start": 1723495921159,
      "end": 1723495921159,
      "order": "normal"
    },
    {
      "name": "vite:vue",
      "result": "\nheader[data-v-a872ff5e] {\n  line-height: 1.5;\n}\n.logo[data-v-a872ff5e] {\n  display: block;\n  margin: 0 auto 2rem;\n}\n@media (min-width: 1024px) {\nheader[data-v-a872ff5e] {\n    display: flex;\n    place-items: center;\n    padding-right: calc(var(--section-gap) / 2);\n}\n.logo[data-v-a872ff5e] {\n    margin: 0 2rem 0 0;\n}\nheader .wrapper[data-v-a872ff5e] {\n    display: flex;\n    place-items: flex-start;\n    flex-wrap: wrap;\n}\n}\n",
      "start": 1723495921159,
      "end": 1723495921270,
      "order": "normal",
      "sourcemaps": {
        "mappings": ""
      }
    },
    {
      "name": "vite:define",
      "start": 1723495921271,
      "end": 1723495921271,
      "order": "normal"
    },
    {
      "name": "vite:css-post",
      "result": "",
      "start": 1723495921273,
      "end": 1723495921273,
      "order": "normal",
      "sourcemaps": {
        "mappings": ""
      }
    },
    {
      "name": "vite:build-html",
      "start": 1723495921274,
      "end": 1723495921274,
      "order": "normal"
    },
    {
      "name": "vite:worker-import-meta-url",
      "start": 1723495921274,
      "end": 1723495921274,
      "order": "normal"
    },
    {
      "name": "vite:asset-import-meta-url",
      "start": 1723495921274,
      "end": 1723495921274,
      "order": "normal"
    },
    {
      "name": "commonjs",
      "start": 1723495921275,
      "end": 1723495921275,
      "order": "normal"
    },
    {
      "name": "vite:dynamic-import-vars",
      "start": 1723495921275,
      "end": 1723495921275,
      "order": "normal"
    },
    {
      "name": "vite:import-glob",
      "start": 1723495921276,
      "end": 1723495921276,
      "order": "normal"
    },
    {
      "name": "vite:build-import-analysis",
      "start": 1723495921276,
      "end": 1723495921276,
      "order": "normal"
    },
    {
      "name": "vite:reporter",
      "start": 1723495921277,
      "end": 1723495921277,
      "order": "normal"
    }
  ]
}
